<?xml version="1.0" encoding="UTF-8"?>
<?xml-stylesheet href="/net_farma_backend_igrp/images/IGRP/IGRP2.3/app/net_farma_app/pagina_dashboard/Pagina_dashboard.xsl" type="text/xsl"?>
<rows>
    <link_img>/net_farma_backend_igrp/images/IGRP/IGRP2.3</link_img>
    <title>Dummie XML prototype</title>
    <site>
        <welcome_note>Oba</welcome_note>
        <footer_note>2019 - Copyright NOSI v.190711</footer_note>
        <user_name>Hexagon</user_name>
        <button type="specific">
            <title>Sair</title>
            <app>DUA</app>
            <page />
            <link>#</link>
            <target>_self</target>
            <img>exit.png</img>
        </button>
    </site>
    <page>Pagina_dashboard</page>
    <app>net_farma_app</app>
    <plsql>
        <action>index</action>
        <package_instance></package_instance>
        <package_db>nosi.webapps.net_farma_app.pages</package_db>
        <package_html>Pagina_dashboard</package_html>
        <table_name></table_name>
        <with_replace>false</with_replace>
        <with_label>false</with_label>
        <with_biztalk>false</with_biztalk>
        <dynamic_menu>false</dynamic_menu>
        <copy_menu>false</copy_menu>
        <package_copy_db />
        <package_copy_html />
        <preserve_url>webapps?r=igrp/page/preserveUrl&amp;p_id=98</preserve_url>
    </plsql>
    <slide-menu file="../images/IGRP/IGRP2.3/xml/IGRP-slide-menu.xml?v=2" />
    <top_menu file="../images/IGRP/IGRP2.3/xml/IGRP-top_menu.xml?v=2" />
    <content>
        <title>Pagina Dashboard</title>
        <toolsbar_1 type="toolsbar" xml-type="toolsbar" gen-type="menu" gen-group="">
            <item type="specific" code="" rel="registrar_produtos" refresh_components="">
                <title>Registrar Produtos</title>
                <app>net_farma_app</app>
                <page>Registrar_medicamento</page>
                <link>index</link>
                <target>_self</target>
                <img>grey|fa-save</img>
                <preview>../images/IGRP/IGRP2.3/app/net_farma_app/registrar_medicamento/Registrar_medicamento.xml</preview>
            </item>
            <item type="specific" code="" rel="listar_produtos" refresh_components="">
                <title>Listar Produtos</title>
                <app>net_farma_app</app>
                <page>Paginalistarproduto</page>
                <link>index</link>
                <target>_self</target>
                <img>grey|fa-list</img>
                <preview>../images/IGRP/IGRP2.3/app/net_farma_app/paginalistarproduto/Paginalistarproduto.xml</preview>
            </item>
            <item type="specific" code="" rel="dashboard" refresh_components="">
                <title>Dashboard</title>
                <app>net_farma_app</app>
                <page>Pagina_dashboard</page>
                <link>index</link>
                <target>_self</target>
                <img>grey|fa-dashboard</img>
                <preview>../images/IGRP/IGRP2.3/app/net_farma_app/pagina_dashboard/Pagina_dashboard.xml</preview>
            </item>
        </toolsbar_1>
        <sectionheader_1 type="sectionheader" xml-type="form" gen-type="container" gen-group="">
            <fields>
                <sectionheader_1_text type="text" name="p_sectionheader_1_text" persist="true" maxlength="4000">
                    <value>
                        <![CDATA[<p><strong><span style='font-family:Times New Roman,Times,serif;'><span style='font-size:36px;'>Dashboarde Farmacia</span></span></strong></p>
]]>
                    </value>
                </sectionheader_1_text>
            </fields>
        </sectionheader_1>
        <circlestatbox_produto type="circlestatbox" xml-type="form" gen-type="container" gen-group="">
            <fields>
                <circlestatbox_produto_title name="p_circlestatbox_produto_title" type="text" maxlength="4000">
                    <label>Circle Box Title</label>
                    <value>Produto</value>
                </circlestatbox_produto_title>
                <circlestatbox_produto_lbl name="p_circlestatbox_produto_lbl" type="text" maxlength="4000">
                    <label>Percent Text</label>
                    <value>percent</value>
                </circlestatbox_produto_lbl>
                <circlestatbox_produto_val name="p_circlestatbox_produto_val" type="text" maxlength="4000">
                    <label>Percent Value</label>
                    <value>62.5</value>
                </circlestatbox_produto_val>
                <circlestatbox_produto_desc name="p_circlestatbox_produto_desc" type="text" maxlength="4000">
                    <label>Description</label>
                    <value>Some Text Here</value>
                </circlestatbox_produto_desc>
                <circlestatbox_produto_url name="p_circlestatbox_produto_url" type="text" maxlength="4000">
                    <label>Link</label>
                    <value>http://www.example.com</value>
                </circlestatbox_produto_url>
                <circlestatbox_produto_bg name="p_circlestatbox_produto_bg" type="text" maxlength="4000">
                    <label>Background</label>
                    <value>cp-cyan</value>
                </circlestatbox_produto_bg>
            </fields>
        </circlestatbox_produto>
        <circlestatbox_estoque type="circlestatbox" xml-type="form" gen-type="container" gen-group="">
            <fields>
                <circlestatbox_estoque_title name="p_circlestatbox_estoque_title" type="text" maxlength="4000">
                    <label>Circle Box Title</label>
                    <value>Total de Produto em Estoque</value>
                </circlestatbox_estoque_title>
                <circlestatbox_estoque_lbl name="p_circlestatbox_estoque_lbl" type="text" maxlength="4000">
                    <label>Percent Text</label>
                    <value>percent</value>
                </circlestatbox_estoque_lbl>
                <circlestatbox_estoque_val name="p_circlestatbox_estoque_val" type="text" maxlength="4000">
                    <label>Percent Value</label>
                    <value>51.4</value>
                </circlestatbox_estoque_val>
                <circlestatbox_estoque_desc name="p_circlestatbox_estoque_desc" type="text" maxlength="4000">
                    <label>Description</label>
                    <value>Some Text Here</value>
                </circlestatbox_estoque_desc>
                <circlestatbox_estoque_url name="p_circlestatbox_estoque_url" type="text" maxlength="4000">
                    <label>Link</label>
                    <value>http://www.example.com</value>
                </circlestatbox_estoque_url>
                <circlestatbox_estoque_bg name="p_circlestatbox_estoque_bg" type="text" maxlength="4000">
                    <label>Background</label>
                    <value>cp-cyan</value>
                </circlestatbox_estoque_bg>
            </fields>
        </circlestatbox_estoque>
        <circlestatbox_funcionario type="circlestatbox" xml-type="form" gen-type="container" gen-group="">
            <fields>
                <circlestatbox_funcionario_title name="p_circlestatbox_funcionario_title" type="text" maxlength="4000">
                    <label>Circle Box Title</label>
                    <value>Funcionario</value>
                </circlestatbox_funcionario_title>
                <circlestatbox_funcionario_lbl name="p_circlestatbox_funcionario_lbl" type="text" maxlength="4000">
                    <label>Percent Text</label>
                    <value>percent</value>
                </circlestatbox_funcionario_lbl>
                <circlestatbox_funcionario_val name="p_circlestatbox_funcionario_val" type="text" maxlength="4000">
                    <label>Percent Value</label>
                    <value>51.1</value>
                </circlestatbox_funcionario_val>
                <circlestatbox_funcionario_desc name="p_circlestatbox_funcionario_desc" type="text" maxlength="4000">
                    <label>Description</label>
                    <value>Some Text Here</value>
                </circlestatbox_funcionario_desc>
                <circlestatbox_funcionario_url name="p_circlestatbox_funcionario_url" type="text" maxlength="4000">
                    <label>Link</label>
                    <value>http://www.example.com</value>
                </circlestatbox_funcionario_url>
                <circlestatbox_funcionario_bg name="p_circlestatbox_funcionario_bg" type="text" maxlength="4000">
                    <label>Background</label>
                    <value>cp-field</value>
                </circlestatbox_funcionario_bg>
            </fields>
        </circlestatbox_funcionario>
        <circlestatbox_fornecedor type="circlestatbox" xml-type="form" gen-type="container" gen-group="">
            <fields>
                <circlestatbox_fornecedor_title name="p_circlestatbox_fornecedor_title" type="text" maxlength="4000">
                    <label>Circle Box Title</label>
                    <value>Fornecedor</value>
                </circlestatbox_fornecedor_title>
                <circlestatbox_fornecedor_lbl name="p_circlestatbox_fornecedor_lbl" type="text" maxlength="4000">
                    <label>Percent Text</label>
                    <value>percent</value>
                </circlestatbox_fornecedor_lbl>
                <circlestatbox_fornecedor_val name="p_circlestatbox_fornecedor_val" type="text" maxlength="4000">
                    <label>Percent Value</label>
                    <value>47.8</value>
                </circlestatbox_fornecedor_val>
                <circlestatbox_fornecedor_desc name="p_circlestatbox_fornecedor_desc" type="text" maxlength="4000">
                    <label>Description</label>
                    <value>Some Text Here</value>
                </circlestatbox_fornecedor_desc>
                <circlestatbox_fornecedor_url name="p_circlestatbox_fornecedor_url" type="text" maxlength="4000">
                    <label>Link</label>
                    <value>http://www.example.com</value>
                </circlestatbox_fornecedor_url>
                <circlestatbox_fornecedor_bg name="p_circlestatbox_fornecedor_bg" type="text" maxlength="4000">
                    <label>Background</label>
                    <value>cp-ink</value>
                </circlestatbox_fornecedor_bg>
            </fields>
        </circlestatbox_fornecedor>
        <circlestatbox_venda type="circlestatbox" xml-type="form" gen-type="container" gen-group="">
            <fields>
                <circlestatbox_venda_title name="p_circlestatbox_venda_title" type="text" maxlength="4000">
                    <label>Circle Box Title</label>
                    <value>Venda</value>
                </circlestatbox_venda_title>
                <circlestatbox_venda_lbl name="p_circlestatbox_venda_lbl" type="text" maxlength="4000">
                    <label>Percent Text</label>
                    <value>percent</value>
                </circlestatbox_venda_lbl>
                <circlestatbox_venda_val name="p_circlestatbox_venda_val" type="text" maxlength="4000">
                    <label>Percent Value</label>
                    <value>60.8</value>
                </circlestatbox_venda_val>
                <circlestatbox_venda_desc name="p_circlestatbox_venda_desc" type="text" maxlength="4000">
                    <label>Description</label>
                    <value>Some Text Here</value>
                </circlestatbox_venda_desc>
                <circlestatbox_venda_url name="p_circlestatbox_venda_url" type="text" maxlength="4000">
                    <label>Link</label>
                    <value>http://www.example.com</value>
                </circlestatbox_venda_url>
                <circlestatbox_venda_bg name="p_circlestatbox_venda_bg" type="text" maxlength="4000">
                    <label>Background</label>
                    <value>cp-lavendar</value>
                </circlestatbox_venda_bg>
            </fields>
        </circlestatbox_venda>
        <circlestatbox_4 type="circlestatbox" xml-type="form" gen-type="container" gen-group="">
            <fields>
                <circlestatbox_4_title name="p_circlestatbox_4_title" type="text" maxlength="4000">
                    <label>Circle Box Title</label>
                    <value>Circle Box Title</value>
                </circlestatbox_4_title>
                <circlestatbox_4_lbl name="p_circlestatbox_4_lbl" type="text" maxlength="4000">
                    <label>Percent Text</label>
                    <value>percent</value>
                </circlestatbox_4_lbl>
                <circlestatbox_4_val name="p_circlestatbox_4_val" type="text" maxlength="4000">
                    <label>Percent Value</label>
                    <value>21.9</value>
                </circlestatbox_4_val>
                <circlestatbox_4_desc name="p_circlestatbox_4_desc" type="text" maxlength="4000">
                    <label>Description</label>
                    <value>Some Text Here</value>
                </circlestatbox_4_desc>
                <circlestatbox_4_url name="p_circlestatbox_4_url" type="text" maxlength="4000">
                    <label>Link</label>
                    <value>http://www.example.com</value>
                </circlestatbox_4_url>
                <circlestatbox_4_bg name="p_circlestatbox_4_bg" type="text" maxlength="4000">
                    <label>Background</label>
                    <value>cp-stylish</value>
                </circlestatbox_4_bg>
            </fields>
        </circlestatbox_4>
        <chart_3 type="chart" xml-type="chart" title="Quantidade de Vendas Anuais por Tipo de Produto" gen-type="container" gen-group="">
            <caption/>
            <chart_type>line</chart_type>
            <xaxys>Eixo de X</xaxys>
            <yaxys>Eixo de Y</yaxys>
            <url>#</url>
            <label>
                <col>Ano</col>
                <col>X1</col>
                <col>X2</col>
                <col>X3</col>
                <col>X4</col>
            </label>
            <value>
                <row>
                    <col>2010</col>
                    <col>84</col>
                    <col>914</col>
                    <col>625</col>
                    <col>177</col>
                </row>
                <row>
                    <col>2009</col>
                    <col>785</col>
                    <col>980</col>
                    <col>763</col>
                    <col>576</col>
                </row>
                <row>
                    <col>2015</col>
                    <col>1010</col>
                    <col>223</col>
                    <col>143</col>
                    <col>78</col>
                </row>
            </value>
            <colors>
                <col>#e17552</col>
                <col>#8b2ef4</col>
                <col>#6940c0</col>
                <col>#b146a3</col>
            </colors>
        </chart_3>
        <chart_2 type="chart" xml-type="chart" title="Quantidade de Produtos Entregues por Fornecedor" gen-type="container" gen-group="">
            <caption/>
            <chart_type>treemap</chart_type>
            <xaxys>Eixo de X</xaxys>
            <yaxys>Eixo de Y</yaxys>
            <url>#</url>
            <label>
                <col>Ano</col>
                <col>X1</col>
                <col>X2</col>
                <col>X3</col>
                <col>X4</col>
            </label>
            <value>
                <row>
                    <col>2010</col>
                    <col>697</col>
                    <col>377</col>
                    <col>74</col>
                    <col>146</col>
                </row>
                <row>
                    <col>2009</col>
                    <col>347</col>
                    <col>605</col>
                    <col>583</col>
                    <col>405</col>
                </row>
                <row>
                    <col>2015</col>
                    <col>1010</col>
                    <col>449</col>
                    <col>911</col>
                    <col>792</col>
                </row>
            </value>
            <colors>
                <col>#209fac</col>
                <col>#5dac52</col>
                <col>#983620</col>
                <col>#6007da</col>
            </colors>
        </chart_2>
        <chart_1 type="chart" xml-type="chart" title="Estoque do Produtos" gen-type="container" gen-group="">
            <caption/>
            <chart_type>area</chart_type>
            <xaxys>Eixo de X</xaxys>
            <yaxys>Eixo de Y</yaxys>
            <url>#</url>
            <label>
                <col>Ano</col>
                <col>X1</col>
                <col>X2</col>
                <col>X3</col>
                <col>X4</col>
            </label>
            <value>
                <row>
                    <col>2010</col>
                    <col>972</col>
                    <col>339</col>
                    <col>848</col>
                    <col>495</col>
                </row>
                <row>
                    <col>2009</col>
                    <col>502</col>
                    <col>248</col>
                    <col>43</col>
                    <col>893</col>
                </row>
                <row>
                    <col>2015</col>
                    <col>1010</col>
                    <col>829</col>
                    <col>563</col>
                    <col>485</col>
                </row>
            </value>
            <colors>
                <col>#d15e60</col>
                <col>#286451</col>
                <col>#f99334</col>
                <col>#eee72a</col>
            </colors>
        </chart_1>
        <form_filtro type="form" xml-type="form" title="Filtro" gen-type="container" gen-group="">
            <fields>
                <nome_do_produto name="p_nome_do_produto" type="text" maxlength="250" required="false" change="false" readonly="false" disabled="false" disablehtml="true" placeholder="" desclabel="false" inputmask="" right="false" tooltip="false" disable_copy_paste="false">
                    <label>Nome do Produto</label>
                    <value>Accusantium anim deserunt laudantium dolor</value>
                </nome_do_produto>
                <status_1 name="p_status_1" type="select" multiple="false" tags="false" load_service_data="false" domain="Status « net_farma_app" maxlength="250" required="false" change="false" disabled="false" right="false" java-type="" tooltip="false" disable_copy_paste="false">
                    <label>Status</label>
                    <list>
                        <option/>
                        <option>
                            <text>Concluido</text>
                            <value>concluída</value>
                        </option>
                        <option>
                            <text>Pendente</text>
                            <value>pendente</value>
                        </option>
                        <option>
                            <text>Cancelada</text>
                            <value>cancelada</value>
                        </option>
                    </list>
                </status_1>
                <data_de name="p_data_de" type="date" range="false" disableWeekends="false" disabledBeforetoday="false" daysoff="false" maxlength="250" required="false" change="false" readonly="false" disabled="false" placeholder="" desclabel="false" right="false" tooltip="false" disable_copy_paste="false" class="success">
                    <label>Data de:</label>
                    <value>08-03-2014</value>
                </data_de>
                <data_ate name="p_data_ate" type="date" range="false" disableWeekends="false" disabledBeforetoday="false" daysoff="false" maxlength="250" required="false" change="false" readonly="false" disabled="false" placeholder="" desclabel="false" right="false" tooltip="false" disable_copy_paste="false" class="danger">
                    <label>Data ate:</label>
                    <value>04-08-2014</value>
                </data_ate>
            </fields>
            <tools-bar>
                <item id="button_3acb_1fef" type="form" code="" class="success" rel="pesquisar" custom_return="true" refresh_components="table_dados_de_venda">
                    <title>Pesquisar</title>
                    <app>net_farma_app</app>
                    <page>Pagina_de_detalhe_de_produto</page>
                    <link>index</link>
                    <parameter>../images/IGRP/IGRP2.3/app/net_farma_app/pagina_de_detalhe_de_produto/Pagina_de_detalhe_de_produto.xml?</parameter>
                    <target>submit_ajax</target>
                    <img>success|fa-search</img>
                    <preview>../images/IGRP/IGRP2.3/app/net_farma_app/pagina_de_detalhe_de_produto/Pagina_de_detalhe_de_produto.xml</preview>
                </item>
            </tools-bar>
        </form_filtro>
        <table_dados_de_venda type="table" xml-type="table" title="Dados de Venda" gen-type="container" gen-group="true">
            <fields>
                <estado name="p_estado" type="color" format="hex" maxlength="30" showLabel="true" align="left" lookup_parser="false" iskey="false" group_in="">
                    <label>Estado</label>
                </estado>
                <nome_de_produto name="p_nome_de_produto" type="text" maxlength="30" showLabel="true" align="left" lookup_parser="false" iskey="false" group_in="">
                    <label>Nome de Produto</label>
                </nome_de_produto>
                <nome_de_produto_1 name="p_nome_de_produto_1" type="text" maxlength="30" showLabel="true" align="left" lookup_parser="false" iskey="false" group_in="">
                    <label>Nome de Produto</label>
                </nome_de_produto_1>
                <tipo_de_produto name="p_tipo_de_produto" type="text" maxlength="30" showLabel="true" align="left" lookup_parser="false" iskey="false" group_in="">
                    <label>Tipo de Produto</label>
                </tipo_de_produto>
                <quantidade name="p_quantidade" type="text" maxlength="30" showLabel="true" align="left" lookup_parser="false" iskey="false" group_in="">
                    <label>Quantidade</label>
                </quantidade>
                <preco_unitario name="p_preco_unitario" type="text" maxlength="30" showLabel="true" align="left" lookup_parser="false" iskey="false" group_in="">
                    <label>Preço Unitario</label>
                </preco_unitario>
                <data_de_venda name="p_data_de_venda" type="text" maxlength="30" showLabel="true" align="left" lookup_parser="false" iskey="false" group_in="">
                    <label>Data de Venda</label>
                </data_de_venda>
                <metodo_de_pagamento name="p_metodo_de_pagamento" type="text" maxlength="30" showLabel="true" align="left" lookup_parser="false" iskey="false" group_in="">
                    <label>Metodo de Pagamento</label>
                </metodo_de_pagamento>
                <valor_total_pago name="p_valor_total_pago" type="text" maxlength="30" showLabel="true" align="left" lookup_parser="false" iskey="false" group_in="">
                    <label>Valor Total Pago</label>
                </valor_total_pago>
            </fields>
            <table>
                <value>
                    <row>
                        <estado name="p_estado">cancelada</estado>
                        <nome_de_produto name="p_nome_de_produto">Sed lorem magna totam anim</nome_de_produto>
                        <nome_de_produto_1 name="p_nome_de_produto_1">Aliqua sed doloremque sit elit</nome_de_produto_1>
                        <tipo_de_produto name="p_tipo_de_produto">Lorem voluptatem sit sit offic</tipo_de_produto>
                        <quantidade name="p_quantidade">Deserunt ut deserunt magna off</quantidade>
                        <preco_unitario name="p_preco_unitario">Dolor sit perspiciatis dolorem</preco_unitario>
                        <data_de_venda name="p_data_de_venda">Omnis mollit consectetur elit</data_de_venda>
                        <metodo_de_pagamento name="p_metodo_de_pagamento">Lorem ipsum officia voluptatem</metodo_de_pagamento>
                        <valor_total_pago name="p_valor_total_pago">Aperiam rem laudantium ipsum u</valor_total_pago>
                    </row>
                    <row>
                        <estado name="p_estado">cancelada</estado>
                        <nome_de_produto name="p_nome_de_produto">Rem aperiam perspiciatis volup</nome_de_produto>
                        <nome_de_produto_1 name="p_nome_de_produto_1">Mollit adipiscing ut amet pers</nome_de_produto_1>
                        <tipo_de_produto name="p_tipo_de_produto">Ut accusantium laudantium natu</tipo_de_produto>
                        <quantidade name="p_quantidade">Mollit natus stract sed lorem</quantidade>
                        <preco_unitario name="p_preco_unitario">Natus unde doloremque omnis si</preco_unitario>
                        <data_de_venda name="p_data_de_venda">Voluptatem perspiciatis unde s</data_de_venda>
                        <metodo_de_pagamento name="p_metodo_de_pagamento">Anim magna lorem voluptatem de</metodo_de_pagamento>
                        <valor_total_pago name="p_valor_total_pago">Aperiam magna elit sit stract</valor_total_pago>
                    </row>
                    <row>
                        <estado name="p_estado">cancelada</estado>
                        <nome_de_produto name="p_nome_de_produto">Totam amet doloremque consecte</nome_de_produto>
                        <nome_de_produto_1 name="p_nome_de_produto_1">Aperiam rem officia sed anim</nome_de_produto_1>
                        <tipo_de_produto name="p_tipo_de_produto">Aliqua sit lorem aliqua rem</tipo_de_produto>
                        <quantidade name="p_quantidade">Sed officia voluptatem aperiam</quantidade>
                        <preco_unitario name="p_preco_unitario">Adipiscing rem iste aperiam om</preco_unitario>
                        <data_de_venda name="p_data_de_venda">Adipiscing consectetur stract</data_de_venda>
                        <metodo_de_pagamento name="p_metodo_de_pagamento">Ut perspiciatis amet rem anim</metodo_de_pagamento>
                        <valor_total_pago name="p_valor_total_pago">Sit elit natus laudantium sit</valor_total_pago>
                    </row>
                    <row>
                        <estado name="p_estado">cancelada</estado>
                        <nome_de_produto name="p_nome_de_produto">Stract dolor laudantium elit l</nome_de_produto>
                        <nome_de_produto_1 name="p_nome_de_produto_1">Adipiscing sit officia iste om</nome_de_produto_1>
                        <tipo_de_produto name="p_tipo_de_produto">Elit consectetur ut sit natus</tipo_de_produto>
                        <quantidade name="p_quantidade">Deserunt unde amet adipiscing</quantidade>
                        <preco_unitario name="p_preco_unitario">Adipiscing accusantium dolor s</preco_unitario>
                        <data_de_venda name="p_data_de_venda">Officia deserunt iste doloremq</data_de_venda>
                        <metodo_de_pagamento name="p_metodo_de_pagamento">Stract dolor aperiam unde dese</metodo_de_pagamento>
                        <valor_total_pago name="p_valor_total_pago">Officia laudantium perspiciati</valor_total_pago>
                    </row>
                    <row>
                        <estado name="p_estado">cancelada</estado>
                        <nome_de_produto name="p_nome_de_produto">Anim rem unde ut sit</nome_de_produto>
                        <nome_de_produto_1 name="p_nome_de_produto_1">Mollit aperiam omnis sed totam</nome_de_produto_1>
                        <tipo_de_produto name="p_tipo_de_produto">Iste unde doloremque accusanti</tipo_de_produto>
                        <quantidade name="p_quantidade">Deserunt mollit omnis sit elit</quantidade>
                        <preco_unitario name="p_preco_unitario">Lorem adipiscing amet rem aliq</preco_unitario>
                        <data_de_venda name="p_data_de_venda">Labore officia sed natus sit</data_de_venda>
                        <metodo_de_pagamento name="p_metodo_de_pagamento">Aliqua perspiciatis sit anim l</metodo_de_pagamento>
                        <valor_total_pago name="p_valor_total_pago">Iste consectetur aperiam volup</valor_total_pago>
                    </row>
                </value>
                <legend_color>
                    <item>
                        <label>cancelado</label>
                        <value>cancelada</value>
                        <color>#dc2b4c</color>
                    </item>
                    <item>
                        <label>pendente</label>
                        <value>pendente</value>
                        <color>#ea9126</color>
                    </item>
                    <item>
                        <label>concluida</label>
                        <value>concluída</value>
                        <color>#95c11f</color>
                    </item>
                </legend_color>
            </table>
        </table_dados_de_venda>
    </content>
    <blockly>
        <imports></imports>
        <xml>
            <block type="controller" id="controller" x="388" y="13"></block>
        </xml>
    </blockly>
</rows>