<?xml version="1.0" encoding="UTF-8"?>
<?xml-stylesheet href="/net_farma_backend_igrp/images/IGRP/IGRP2.3/app/net_farma_app/pagina_dashboard/Pagina_dashboard.xsl" type="text/xsl"?>
<rows>
    <link_img>/net_farma_backend_igrp/images/IGRP/IGRP2.3</link_img>
    <title>Dummie XML prototype</title>
    <site>
        <welcome_note>Oba</welcome_note>
        <footer_note>2019 - Copyright NOSI v.190711</footer_note>
        <user_name>Hexagon</user_name>
        <button type="specific">
            <title>Sair</title>
            <app>DUA</app>
            <page />
            <link>#</link>
            <target>_self</target>
            <img>exit.png</img>
        </button>
    </site>
    <page>Pagina_dashboard</page>
    <app>net_farma_app</app>
    <plsql>
        <action>index</action>
        <package_instance></package_instance>
        <package_db>nosi.webapps.net_farma_app.pages</package_db>
        <package_html>Pagina_dashboard</package_html>
        <table_name></table_name>
        <with_replace>false</with_replace>
        <with_label>false</with_label>
        <with_biztalk>false</with_biztalk>
        <dynamic_menu>false</dynamic_menu>
        <copy_menu>false</copy_menu>
        <package_copy_db />
        <package_copy_html />
        <preserve_url>webapps?r=igrp/page/preserveUrl&amp;p_id=98</preserve_url>
    </plsql>
    <slide-menu file="../images/IGRP/IGRP2.3/xml/IGRP-slide-menu.xml?v=2" />
    <top_menu file="../images/IGRP/IGRP2.3/xml/IGRP-top_menu.xml?v=2" />
    <content>
        <title>Pagina Dashboard</title>
        <toolsbar_1 type="toolsbar" xml-type="toolsbar" gen-type="menu" gen-group="">
            <item type="specific" code="" rel="registrar_produtos" refresh_components="">
                <title>Registrar Produtos</title>
                <app>net_farma_app</app>
                <page>Registrar_medicamento</page>
                <link>index</link>
                <target>_self</target>
                <img>grey|fa-save</img>
                <preview>../images/IGRP/IGRP2.3/app/net_farma_app/registrar_medicamento/Registrar_medicamento.xml</preview>
            </item>
            <item type="specific" code="" rel="listar_produtos" refresh_components="">
                <title>Listar Produtos</title>
                <app>net_farma_app</app>
                <page>Paginalistarproduto</page>
                <link>index</link>
                <target>_self</target>
                <img>grey|fa-list</img>
                <preview>../images/IGRP/IGRP2.3/app/net_farma_app/paginalistarproduto/Paginalistarproduto.xml</preview>
            </item>
            <item type="specific" code="" rel="dashboard" refresh_components="">
                <title>Dashboard</title>
                <app>net_farma_app</app>
                <page>Pagina_dashboard</page>
                <link>index</link>
                <target>_self</target>
                <img>grey|fa-dashboard</img>
                <preview>../images/IGRP/IGRP2.3/app/net_farma_app/pagina_dashboard/Pagina_dashboard.xml</preview>
            </item>
        </toolsbar_1>
        <sectionheader_1 type="sectionheader" xml-type="form" gen-type="container" gen-group="">
            <fields>
                <sectionheader_1_text type="text" name="p_sectionheader_1_text" persist="true" maxlength="4000">
                    <value>
                        <![CDATA[<p><strong><span style='font-family:Times New Roman,Times,serif;'><span style='font-size:36px;'>Dashboarde Farmacia</span></span></strong></p>
]]>
                    </value>
                </sectionheader_1_text>
            </fields>
        </sectionheader_1>
        <circlestatbox_produto type="circlestatbox" xml-type="form" gen-type="container" gen-group="">
            <fields>
                <circlestatbox_produto_title name="p_circlestatbox_produto_title" type="text" maxlength="4000">
                    <label>Circle Box Title</label>
                    <value>Produto</value>
                </circlestatbox_produto_title>
                <circlestatbox_produto_lbl name="p_circlestatbox_produto_lbl" type="text" maxlength="4000">
                    <label>Percent Text</label>
                    <value>percent</value>
                </circlestatbox_produto_lbl>
                <circlestatbox_produto_val name="p_circlestatbox_produto_val" type="text" maxlength="4000">
                    <label>Percent Value</label>
                    <value>62.5</value>
                </circlestatbox_produto_val>
                <circlestatbox_produto_desc name="p_circlestatbox_produto_desc" type="text" maxlength="4000">
                    <label>Description</label>
                    <value>Some Text Here</value>
                </circlestatbox_produto_desc>
                <circlestatbox_produto_url name="p_circlestatbox_produto_url" type="text" maxlength="4000">
                    <label>Link</label>
                    <value>http://www.example.com</value>
                </circlestatbox_produto_url>
                <circlestatbox_produto_bg name="p_circlestatbox_produto_bg" type="text" maxlength="4000">
                    <label>Background</label>
                    <value>cp-cyan</value>
                </circlestatbox_produto_bg>
            </fields>
        </circlestatbox_produto>
        <circlestatbox_estoque type="circlestatbox" xml-type="form" gen-type="container" gen-group="">
            <fields>
                <circlestatbox_estoque_title name="p_circlestatbox_estoque_title" type="text" maxlength="4000">
                    <label>Circle Box Title</label>
                    <value>Total de Produto em Estoque</value>
                </circlestatbox_estoque_title>
                <circlestatbox_estoque_lbl name="p_circlestatbox_estoque_lbl" type="text" maxlength="4000">
                    <label>Percent Text</label>
                    <value>percent</value>
                </circlestatbox_estoque_lbl>
                <circlestatbox_estoque_val name="p_circlestatbox_estoque_val" type="text" maxlength="4000">
                    <label>Percent Value</label>
                    <value>51.4</value>
                </circlestatbox_estoque_val>
                <circlestatbox_estoque_desc name="p_circlestatbox_estoque_desc" type="text" maxlength="4000">
                    <label>Description</label>
                    <value>Some Text Here</value>
                </circlestatbox_estoque_desc>
                <circlestatbox_estoque_url name="p_circlestatbox_estoque_url" type="text" maxlength="4000">
                    <label>Link</label>
                    <value>http://www.example.com</value>
                </circlestatbox_estoque_url>
                <circlestatbox_estoque_bg name="p_circlestatbox_estoque_bg" type="text" maxlength="4000">
                    <label>Background</label>
                    <value>cp-cyan</value>
                </circlestatbox_estoque_bg>
            </fields>
        </circlestatbox_estoque>
        <circlestatbox_funcionario type="circlestatbox" xml-type="form" gen-type="container" gen-group="">
            <fields>
                <circlestatbox_funcionario_title name="p_circlestatbox_funcionario_title" type="text" maxlength="4000">
                    <label>Circle Box Title</label>
                    <value>Funcionario</value>
                </circlestatbox_funcionario_title>
                <circlestatbox_funcionario_lbl name="p_circlestatbox_funcionario_lbl" type="text" maxlength="4000">
                    <label>Percent Text</label>
                    <value>percent</value>
                </circlestatbox_funcionario_lbl>
                <circlestatbox_funcionario_val name="p_circlestatbox_funcionario_val" type="text" maxlength="4000">
                    <label>Percent Value</label>
                    <value>51.1</value>
                </circlestatbox_funcionario_val>
                <circlestatbox_funcionario_desc name="p_circlestatbox_funcionario_desc" type="text" maxlength="4000">
                    <label>Description</label>
                    <value>Some Text Here</value>
                </circlestatbox_funcionario_desc>
                <circlestatbox_funcionario_url name="p_circlestatbox_funcionario_url" type="text" maxlength="4000">
                    <label>Link</label>
                    <value>http://www.example.com</value>
                </circlestatbox_funcionario_url>
                <circlestatbox_funcionario_bg name="p_circlestatbox_funcionario_bg" type="text" maxlength="4000">
                    <label>Background</label>
                    <value>cp-field</value>
                </circlestatbox_funcionario_bg>
            </fields>
        </circlestatbox_funcionario>
        <circlestatbox_fornecedor type="circlestatbox" xml-type="form" gen-type="container" gen-group="">
            <fields>
                <circlestatbox_fornecedor_title name="p_circlestatbox_fornecedor_title" type="text" maxlength="4000">
                    <label>Circle Box Title</label>
                    <value>Fornecedor</value>
                </circlestatbox_fornecedor_title>
                <circlestatbox_fornecedor_lbl name="p_circlestatbox_fornecedor_lbl" type="text" maxlength="4000">
                    <label>Percent Text</label>
                    <value>percent</value>
                </circlestatbox_fornecedor_lbl>
                <circlestatbox_fornecedor_val name="p_circlestatbox_fornecedor_val" type="text" maxlength="4000">
                    <label>Percent Value</label>
                    <value>47.8</value>
                </circlestatbox_fornecedor_val>
                <circlestatbox_fornecedor_desc name="p_circlestatbox_fornecedor_desc" type="text" maxlength="4000">
                    <label>Description</label>
                    <value>Some Text Here</value>
                </circlestatbox_fornecedor_desc>
                <circlestatbox_fornecedor_url name="p_circlestatbox_fornecedor_url" type="text" maxlength="4000">
                    <label>Link</label>
                    <value>http://www.example.com</value>
                </circlestatbox_fornecedor_url>
                <circlestatbox_fornecedor_bg name="p_circlestatbox_fornecedor_bg" type="text" maxlength="4000">
                    <label>Background</label>
                    <value>cp-ink</value>
                </circlestatbox_fornecedor_bg>
            </fields>
        </circlestatbox_fornecedor>
        <circlestatbox_venda type="circlestatbox" xml-type="form" gen-type="container" gen-group="">
            <fields>
                <circlestatbox_venda_title name="p_circlestatbox_venda_title" type="text" maxlength="4000">
                    <label>Circle Box Title</label>
                    <value>Venda</value>
                </circlestatbox_venda_title>
                <circlestatbox_venda_lbl name="p_circlestatbox_venda_lbl" type="text" maxlength="4000">
                    <label>Percent Text</label>
                    <value>percent</value>
                </circlestatbox_venda_lbl>
                <circlestatbox_venda_val name="p_circlestatbox_venda_val" type="text" maxlength="4000">
                    <label>Percent Value</label>
                    <value>60.8</value>
                </circlestatbox_venda_val>
                <circlestatbox_venda_desc name="p_circlestatbox_venda_desc" type="text" maxlength="4000">
                    <label>Description</label>
                    <value>Some Text Here</value>
                </circlestatbox_venda_desc>
                <circlestatbox_venda_url name="p_circlestatbox_venda_url" type="text" maxlength="4000">
                    <label>Link</label>
                    <value>http://www.example.com</value>
                </circlestatbox_venda_url>
                <circlestatbox_venda_bg name="p_circlestatbox_venda_bg" type="text" maxlength="4000">
                    <label>Background</label>
                    <value>cp-lavendar</value>
                </circlestatbox_venda_bg>
            </fields>
        </circlestatbox_venda>
        <circlestatbox_4 type="circlestatbox" xml-type="form" gen-type="container" gen-group="">
            <fields>
                <circlestatbox_4_title name="p_circlestatbox_4_title" type="text" maxlength="4000">
                    <label>Circle Box Title</label>
                    <value>Circle Box Title</value>
                </circlestatbox_4_title>
                <circlestatbox_4_lbl name="p_circlestatbox_4_lbl" type="text" maxlength="4000">
                    <label>Percent Text</label>
                    <value>percent</value>
                </circlestatbox_4_lbl>
                <circlestatbox_4_val name="p_circlestatbox_4_val" type="text" maxlength="4000">
                    <label>Percent Value</label>
                    <value>21.9</value>
                </circlestatbox_4_val>
                <circlestatbox_4_desc name="p_circlestatbox_4_desc" type="text" maxlength="4000">
                    <label>Description</label>
                    <value>Some Text Here</value>
                </circlestatbox_4_desc>
                <circlestatbox_4_url name="p_circlestatbox_4_url" type="text" maxlength="4000">
                    <label>Link</label>
                    <value>http://www.example.com</value>
                </circlestatbox_4_url>
                <circlestatbox_4_bg name="p_circlestatbox_4_bg" type="text" maxlength="4000">
                    <label>Background</label>
                    <value>cp-stylish</value>
                </circlestatbox_4_bg>
            </fields>
        </circlestatbox_4>
        <chart_3 type="chart" xml-type="chart" title="Quantidade de Vendas Anuais por Tipo de Produto" gen-type="container" gen-group="">
            <caption/>
            <chart_type>line</chart_type>
            <xaxys>Eixo de X</xaxys>
            <yaxys>Eixo de Y</yaxys>
            <url>#</url>
            <label>
                <col>Ano</col>
                <col>X1</col>
                <col>X2</col>
                <col>X3</col>
                <col>X4</col>
            </label>
            <value>
                <row>
                    <col>2010</col>
                    <col>823</col>
                    <col>297</col>
                    <col>498</col>
                    <col>945</col>
                </row>
                <row>
                    <col>2009</col>
                    <col>828</col>
                    <col>325</col>
                    <col>692</col>
                    <col>716</col>
                </row>
                <row>
                    <col>2015</col>
                    <col>1010</col>
                    <col>66</col>
                    <col>914</col>
                    <col>912</col>
                </row>
            </value>
            <colors>
                <col>#c1bf9f</col>
                <col>#294497</col>
                <col>#1c71ed</col>
                <col>#c55073</col>
            </colors>
        </chart_3>
        <chart_2 type="chart" xml-type="chart" title="Quantidade de Produtos Entregues por Fornecedor" gen-type="container" gen-group="">
            <caption/>
            <chart_type>treemap</chart_type>
            <xaxys>Eixo de X</xaxys>
            <yaxys>Eixo de Y</yaxys>
            <url>#</url>
            <label>
                <col>Ano</col>
                <col>X1</col>
                <col>X2</col>
                <col>X3</col>
                <col>X4</col>
            </label>
            <value>
                <row>
                    <col>2010</col>
                    <col>388</col>
                    <col>344</col>
                    <col>413</col>
                    <col>855</col>
                </row>
                <row>
                    <col>2009</col>
                    <col>934</col>
                    <col>573</col>
                    <col>847</col>
                    <col>512</col>
                </row>
                <row>
                    <col>2015</col>
                    <col>1010</col>
                    <col>668</col>
                    <col>223</col>
                    <col>106</col>
                </row>
            </value>
            <colors>
                <col>#353a24</col>
                <col>#e9bd0a</col>
                <col>#78fbdd</col>
                <col>#a53141</col>
            </colors>
        </chart_2>
        <chart_1 type="chart" xml-type="chart" title="Estoque do Produtos" gen-type="container" gen-group="">
            <caption/>
            <chart_type>area</chart_type>
            <xaxys>Eixo de X</xaxys>
            <yaxys>Eixo de Y</yaxys>
            <url>#</url>
            <label>
                <col>Ano</col>
                <col>X1</col>
                <col>X2</col>
                <col>X3</col>
                <col>X4</col>
            </label>
            <value>
                <row>
                    <col>2010</col>
                    <col>850</col>
                    <col>760</col>
                    <col>672</col>
                    <col>945</col>
                </row>
                <row>
                    <col>2009</col>
                    <col>974</col>
                    <col>173</col>
                    <col>681</col>
                    <col>41</col>
                </row>
                <row>
                    <col>2015</col>
                    <col>1010</col>
                    <col>678</col>
                    <col>848</col>
                    <col>483</col>
                </row>
            </value>
            <colors>
                <col>#674ed0</col>
                <col>#acd841</col>
                <col>#fd530f</col>
                <col>#8365f1</col>
            </colors>
        </chart_1>
        <table_dados_de_venda type="table" xml-type="table" title="Dados de Venda" gen-type="container" gen-group="true">
            <fields>
                <estado name="p_estado" type="text" maxlength="30" showLabel="true" align="left" lookup_parser="false" iskey="false" group_in="">
                    <label>Estado</label>
                </estado>
                <nome_de_produto name="p_nome_de_produto" type="text" maxlength="30" showLabel="true" align="left" lookup_parser="false" iskey="false" group_in="">
                    <label>Nome de Produto</label>
                </nome_de_produto>
                <nome_de_produto_1 name="p_nome_de_produto_1" type="text" maxlength="30" showLabel="true" align="left" lookup_parser="false" iskey="false" group_in="">
                    <label>Nome de Produto</label>
                </nome_de_produto_1>
                <tipo_de_produto name="p_tipo_de_produto" type="text" maxlength="30" showLabel="true" align="left" lookup_parser="false" iskey="false" group_in="">
                    <label>Tipo de Produto</label>
                </tipo_de_produto>
                <quantidade name="p_quantidade" type="text" maxlength="30" showLabel="true" align="left" lookup_parser="false" iskey="false" group_in="">
                    <label>Quantidade</label>
                </quantidade>
                <preco_unitario name="p_preco_unitario" type="text" maxlength="30" showLabel="true" align="left" lookup_parser="false" iskey="false" group_in="">
                    <label>Preço Unitario</label>
                </preco_unitario>
                <data_de_venda name="p_data_de_venda" type="text" maxlength="30" showLabel="true" align="left" lookup_parser="false" iskey="false" group_in="">
                    <label>Data de Venda</label>
                </data_de_venda>
                <metodo_de_pagamento name="p_metodo_de_pagamento" type="text" maxlength="30" showLabel="true" align="left" lookup_parser="false" iskey="false" group_in="">
                    <label>Metodo de Pagamento</label>
                </metodo_de_pagamento>
                <valor_total_pago name="p_valor_total_pago" type="text" maxlength="30" showLabel="true" align="left" lookup_parser="false" iskey="false" group_in="">
                    <label>Valor Total Pago</label>
                </valor_total_pago>
            </fields>
            <table>
                <value>
                    <row>
                        <estado name="p_estado">Perspiciatis laudantium deseru</estado>
                        <nome_de_produto name="p_nome_de_produto">Mollit ipsum officia aperiam s</nome_de_produto>
                        <nome_de_produto_1 name="p_nome_de_produto_1">Unde anim voluptatem magna des</nome_de_produto_1>
                        <tipo_de_produto name="p_tipo_de_produto">Labore unde labore accusantium</tipo_de_produto>
                        <quantidade name="p_quantidade">Ut perspiciatis voluptatem lab</quantidade>
                        <preco_unitario name="p_preco_unitario">Rem doloremque officia mollit</preco_unitario>
                        <data_de_venda name="p_data_de_venda">Adipiscing ut anim officia ali</data_de_venda>
                        <metodo_de_pagamento name="p_metodo_de_pagamento">Adipiscing omnis totam dolor r</metodo_de_pagamento>
                        <valor_total_pago name="p_valor_total_pago">Accusantium officia ipsum iste</valor_total_pago>
                    </row>
                    <row>
                        <estado name="p_estado">Unde ipsum voluptatem lorem am</estado>
                        <nome_de_produto name="p_nome_de_produto">Deserunt sit anim magna rem</nome_de_produto>
                        <nome_de_produto_1 name="p_nome_de_produto_1">Natus sit mollit doloremque do</nome_de_produto_1>
                        <tipo_de_produto name="p_tipo_de_produto">Stract ipsum totam natus aliqu</tipo_de_produto>
                        <quantidade name="p_quantidade">Natus unde consectetur iste om</quantidade>
                        <preco_unitario name="p_preco_unitario">Sed perspiciatis laudantium ad</preco_unitario>
                        <data_de_venda name="p_data_de_venda">Ipsum lorem ut anim consectetu</data_de_venda>
                        <metodo_de_pagamento name="p_metodo_de_pagamento">Sit natus voluptatem laudantiu</metodo_de_pagamento>
                        <valor_total_pago name="p_valor_total_pago">Magna iste sit sit consectetur</valor_total_pago>
                    </row>
                    <row>
                        <estado name="p_estado">Iste consectetur lorem adipisc</estado>
                        <nome_de_produto name="p_nome_de_produto">Deserunt sit sit ipsum perspic</nome_de_produto>
                        <nome_de_produto_1 name="p_nome_de_produto_1">Aperiam dolor doloremque lorem</nome_de_produto_1>
                        <tipo_de_produto name="p_tipo_de_produto">Unde mollit unde anim unde</tipo_de_produto>
                        <quantidade name="p_quantidade">Perspiciatis labore doloremque</quantidade>
                        <preco_unitario name="p_preco_unitario">Accusantium aperiam totam accu</preco_unitario>
                        <data_de_venda name="p_data_de_venda">Sed sit deserunt adipiscing si</data_de_venda>
                        <metodo_de_pagamento name="p_metodo_de_pagamento">Rem iste aperiam sed deserunt</metodo_de_pagamento>
                        <valor_total_pago name="p_valor_total_pago">Perspiciatis lorem officia ani</valor_total_pago>
                    </row>
                    <row>
                        <estado name="p_estado">Rem sed voluptatem laudantium</estado>
                        <nome_de_produto name="p_nome_de_produto">Perspiciatis sit officia magna</nome_de_produto>
                        <nome_de_produto_1 name="p_nome_de_produto_1">Totam rem consectetur ut sit</nome_de_produto_1>
                        <tipo_de_produto name="p_tipo_de_produto">Amet anim totam aliqua ipsum</tipo_de_produto>
                        <quantidade name="p_quantidade">Labore ipsum lorem doloremque</quantidade>
                        <preco_unitario name="p_preco_unitario">Consectetur deserunt labore si</preco_unitario>
                        <data_de_venda name="p_data_de_venda">Mollit perspiciatis elit anim</data_de_venda>
                        <metodo_de_pagamento name="p_metodo_de_pagamento">Rem aperiam lorem natus mollit</metodo_de_pagamento>
                        <valor_total_pago name="p_valor_total_pago">Lorem sit accusantium aliqua a</valor_total_pago>
                    </row>
                    <row>
                        <estado name="p_estado">Aperiam adipiscing perspiciati</estado>
                        <nome_de_produto name="p_nome_de_produto">Amet sit labore lorem elit</nome_de_produto>
                        <nome_de_produto_1 name="p_nome_de_produto_1">Aliqua doloremque ut natus per</nome_de_produto_1>
                        <tipo_de_produto name="p_tipo_de_produto">Accusantium lorem laudantium u</tipo_de_produto>
                        <quantidade name="p_quantidade">Aliqua doloremque ut amet pers</quantidade>
                        <preco_unitario name="p_preco_unitario">Adipiscing deserunt laudantium</preco_unitario>
                        <data_de_venda name="p_data_de_venda">Lorem omnis doloremque laudant</data_de_venda>
                        <metodo_de_pagamento name="p_metodo_de_pagamento">Ipsum dolor adipiscing anim la</metodo_de_pagamento>
                        <valor_total_pago name="p_valor_total_pago">Laudantium sit ut natus rem</valor_total_pago>
                    </row>
                </value>
            </table>
        </table_dados_de_venda>
    </content>
    <blockly>
        <imports></imports>
        <xml>
            <block type="controller" id="controller" x="388" y="13"></block>
        </xml>
    </blockly>
</rows>